{
    "criteria": {
        "remove_spawn": {
            "trigger": "using_item",
            "conditions": {
                "player": [
                    {
                        "condition": "reference",
                        "name": "cwm:this/has_spawn"
                    }
                ],
                "item": {
                    "items": "structure_void",
                    "count": 1,
                    "components": {
                        "custom_data": {
                            "spawn": {
                                "remove": 1
                            },
                            "cwm": 1
                        }
                    }
                }
            }
        }
    },
    "requirements": [
        [
            "remove_spawn"
        ]
    ],
    "rewards": {
        "function": "cwm:events/remove_spawn"
    },
    "sends_telemetry_event": true
}
